nvalues/VERSION
nvalues/__init__.py
nvalues/cube.py
nvalues/exceptions.py
nvalues/grid.py
nvalues/line.py
nvalues/penteract.py
nvalues/py.typed
nvalues/tesseract.py
nvalues/types.py
nvalues/value.py
nvalues/volume.py
nvalues-1.0.0b6.dist-info/LICENSE
nvalues-1.0.0b6.dist-info/METADATA
nvalues-1.0.0b6.dist-info/WHEEL
nvalues-1.0.0b6.dist-info/top_level.txt
nvalues-1.0.0b6.dist-info/RECORD
